cactus_schema/__init__.py
cactus_schema/py.typed
cactus_schema/notification/__init__.py
cactus_schema/notification/schema.py
cactus_schema/notification/uri.py
cactus_schema/orchestrator/__init__.py
cactus_schema/orchestrator/schema.py
cactus_schema/orchestrator/uri.py
cactus_schema/runner/__init__.py
cactus_schema/runner/schema.py
cactus_schema/runner/uri.py
cactus_schema-0.0.10.dist-info/licenses/LICENSE
cactus_schema-0.0.10.dist-info/METADATA
cactus_schema-0.0.10.dist-info/WHEEL
cactus_schema-0.0.10.dist-info/top_level.txt
cactus_schema-0.0.10.dist-info/RECORD
